[
  {
    "0": {
      "precision": 0.9831932773109243,
      "recall": 0.78,
      "f1-score": 0.8698884758364313,
      "support": 300.0
    },
    "1": {
      "precision": 0.8176795580110497,
      "recall": 0.9866666666666667,
      "f1-score": 0.8942598187311179,
      "support": 300.0
    },
    "accuracy": 0.8833333333333333,
    "macro avg": {
      "precision": 0.900436417660987,
      "recall": 0.8833333333333333,
      "f1-score": 0.8820741472837745,
      "support": 600.0
    },
    "weighted avg": {
      "precision": 0.900436417660987,
      "recall": 0.8833333333333333,
      "f1-score": 0.8820741472837744,
      "support": 600.0
    }
  },
  {
    "0": {
      "precision": 0.9833333333333333,
      "recall": 0.7866666666666666,
      "f1-score": 0.8740740740740739,
      "support": 300.0
    },
    "1": {
      "precision": 0.8222222222222222,
      "recall": 0.9866666666666667,
      "f1-score": 0.896969696969697,
      "support": 300.0
    },
    "accuracy": 0.8866666666666667,
    "macro avg": {
      "precision": 0.9027777777777777,
      "recall": 0.8866666666666667,
      "f1-score": 0.8855218855218854,
      "support": 600.0
    },
    "weighted avg": {
      "precision": 0.9027777777777777,
      "recall": 0.8866666666666667,
      "f1-score": 0.8855218855218853,
      "support": 600.0
    }
  },
  {
    "0": {
      "precision": 0.9958333333333333,
      "recall": 0.7966666666666666,
      "f1-score": 0.8851851851851852,
      "support": 300.0
    },
    "1": {
      "precision": 0.8305555555555556,
      "recall": 0.9966666666666667,
      "f1-score": 0.9060606060606061,
      "support": 300.0
    },
    "accuracy": 0.8966666666666666,
    "macro avg": {
      "precision": 0.9131944444444444,
      "recall": 0.8966666666666667,
      "f1-score": 0.8956228956228957,
      "support": 600.0
    },
    "weighted avg": {
      "precision": 0.9131944444444445,
      "recall": 0.8966666666666666,
      "f1-score": 0.8956228956228957,
      "support": 600.0
    }
  },
  {
    "0": {
      "precision": 0.9752066115702479,
      "recall": 0.7866666666666666,
      "f1-score": 0.8708487084870848,
      "support": 300.0
    },
    "1": {
      "precision": 0.8212290502793296,
      "recall": 0.98,
      "f1-score": 0.8936170212765957,
      "support": 300.0
    },
    "accuracy": 0.8833333333333333,
    "macro avg": {
      "precision": 0.8982178309247888,
      "recall": 0.8833333333333333,
      "f1-score": 0.8822328648818403,
      "support": 600.0
    },
    "weighted avg": {
      "precision": 0.8982178309247888,
      "recall": 0.8833333333333333,
      "f1-score": 0.8822328648818403,
      "support": 600.0
    }
  },
  {
    "0": {
      "precision": 0.9835390946502057,
      "recall": 0.7966666666666666,
      "f1-score": 0.8802946593001842,
      "support": 300.0
    },
    "1": {
      "precision": 0.8291316526610645,
      "recall": 0.9866666666666667,
      "f1-score": 0.9010654490106544,
      "support": 300.0
    },
    "accuracy": 0.8916666666666667,
    "macro avg": {
      "precision": 0.9063353736556351,
      "recall": 0.8916666666666666,
      "f1-score": 0.8906800541554194,
      "support": 600.0
    },
    "weighted avg": {
      "precision": 0.9063353736556352,
      "recall": 0.8916666666666667,
      "f1-score": 0.8906800541554194,
      "support": 600.0
    }
  },
  {
    "0": {
      "precision": 0.9834710743801653,
      "recall": 0.7933333333333333,
      "f1-score": 0.8782287822878228,
      "support": 300.0
    },
    "1": {
      "precision": 0.8268156424581006,
      "recall": 0.9866666666666667,
      "f1-score": 0.899696048632219,
      "support": 300.0
    },
    "accuracy": 0.89,
    "macro avg": {
      "precision": 0.905143358419133,
      "recall": 0.89,
      "f1-score": 0.8889624154600209,
      "support": 600.0
    },
    "weighted avg": {
      "precision": 0.905143358419133,
      "recall": 0.89,
      "f1-score": 0.8889624154600209,
      "support": 600.0
    }
  },
  {
    "0": {
      "precision": 0.9836734693877551,
      "recall": 0.8033333333333333,
      "f1-score": 0.8844036697247706,
      "support": 300.0
    },
    "1": {
      "precision": 0.8338028169014085,
      "recall": 0.9866666666666667,
      "f1-score": 0.9038167938931297,
      "support": 300.0
    },
    "accuracy": 0.895,
    "macro avg": {
      "precision": 0.9087381431445818,
      "recall": 0.895,
      "f1-score": 0.8941102318089502,
      "support": 600.0
    },
    "weighted avg": {
      "precision": 0.9087381431445817,
      "recall": 0.895,
      "f1-score": 0.8941102318089501,
      "support": 600.0
    }
  },
  {
    "0": {
      "precision": 0.9874476987447699,
      "recall": 0.7866666666666666,
      "f1-score": 0.8756957328385899,
      "support": 300.0
    },
    "1": {
      "precision": 0.8227146814404432,
      "recall": 0.99,
      "f1-score": 0.8986384266263238,
      "support": 300.0
    },
    "accuracy": 0.8883333333333333,
    "macro avg": {
      "precision": 0.9050811900926066,
      "recall": 0.8883333333333333,
      "f1-score": 0.8871670797324569,
      "support": 600.0
    },
    "weighted avg": {
      "precision": 0.9050811900926067,
      "recall": 0.8883333333333333,
      "f1-score": 0.8871670797324568,
      "support": 600.0
    }
  },
  {
    "0": {
      "precision": 0.983739837398374,
      "recall": 0.8066666666666666,
      "f1-score": 0.8864468864468864,
      "support": 300.0
    },
    "1": {
      "precision": 0.8361581920903954,
      "recall": 0.9866666666666667,
      "f1-score": 0.9051987767584098,
      "support": 300.0
    },
    "accuracy": 0.8966666666666666,
    "macro avg": {
      "precision": 0.9099490147443847,
      "recall": 0.8966666666666667,
      "f1-score": 0.8958228316026481,
      "support": 600.0
    },
    "weighted avg": {
      "precision": 0.9099490147443847,
      "recall": 0.8966666666666666,
      "f1-score": 0.8958228316026481,
      "support": 600.0
    }
  },
  {
    "0": {
      "precision": 0.9748953974895398,
      "recall": 0.7766666666666666,
      "f1-score": 0.8645640074211502,
      "support": 300.0
    },
    "1": {
      "precision": 0.814404432132964,
      "recall": 0.98,
      "f1-score": 0.8895612708018155,
      "support": 300.0
    },
    "accuracy": 0.8783333333333333,
    "macro avg": {
      "precision": 0.8946499148112519,
      "recall": 0.8783333333333333,
      "f1-score": 0.8770626391114829,
      "support": 600.0
    },
    "weighted avg": {
      "precision": 0.8946499148112518,
      "recall": 0.8783333333333333,
      "f1-score": 0.8770626391114827,
      "support": 600.0
    }
  }
]